dekdjtools-0.1.90.dist-info/METADATA
dekdjtools-0.1.90.dist-info/WHEEL
dekdjtools-0.1.90.dist-info/entry_points.txt
dekdjtools/__init__.py
dekdjtools/admin/__init__.py
dekdjtools/admin/base/__init__.py
dekdjtools/apps.py
dekdjtools/console.py
dekdjtools/dekshellplugin/__init__.py
dekdjtools/dekshellplugin/markers/__init__.py
dekdjtools/fields/__init__.py
dekdjtools/fields/data.py
dekdjtools/fields/image.py
dekdjtools/fields/snowflake.py
dekdjtools/fields/snowflakeid.py
dekdjtools/fields/url.py
dekdjtools/management/__init__.py
dekdjtools/management/base/__init__.py
dekdjtools/management/commands/__init__.py
dekdjtools/management/commands/backup.py
dekdjtools/management/commands/dbbackupclean.py
dekdjtools/management/commands/dbbackuppath.py
dekdjtools/management/commands/dbbackupsetup.py
dekdjtools/management/commands/ddtdbreset.py
dekdjtools/management/commands/ddtdelmigrations.py
dekdjtools/management/commands/ensuresuperuser.py
dekdjtools/management/commands/restore.py
dekdjtools/management/commands/utils/__init__.py
dekdjtools/migrations/__init__.py
dekdjtools/models/__init__.py
dekdjtools/models/base/__init__.py
dekdjtools/psqlextra/__init__.py
dekdjtools/psqlextra/migrations/__init__.py
dekdjtools/psqlextra/migrations/fk.py
dekdjtools/psqlextra/migrations/hash.py
dekdjtools/psqlextra/migrations/list.py
dekdjtools/psqlextra/models/__init__.py
dekdjtools/psqlextra/models/fk.py
dekdjtools/psqlextra/utils.py
dekdjtools/settings.py
dekdjtools/settings_app.py
dekdjtools/settings_generate.py
dekdjtools/snowflake.py
dekdjtools/static/dekdjtools/float-window/index.css
dekdjtools/static/dekdjtools/float-window/index.js
dekdjtools/static/dekdjtools/toastify-js/toastify.js
dekdjtools/static/dekdjtools/toastify-js/toastify.min.css
dekdjtools/templates/admin/change_list.html
dekdjtools/unionid.py
dekdjtools/utils/__init__.py
dekdjtools/utils/common.py
dekdjtools/utils/django.py
dekdjtools/utils/finder.py
dekdjtools/utils/format.py
dekdjtools/utils/media.py
dekdjtools/utils/migration.py
dekdjtools/utils/model.py
dekdjtools/utils/query.py
dekdjtools/utils/req.py
dekdjtools/utils/user.py
dekdjtools-0.1.90.dist-info/RECORD
