Metadata-Version: 2.1
Name: dekdjtools
Version: 0.1.90
Author-Email: sanzenwin <sanzenwin@gmail.com>
License: MIT
Requires-Python: >=3.10
Requires-Dist: django==4.2.16
Requires-Dist: django-extensions<=3.2.3
Requires-Dist: djangorestframework<=3.15.2
Requires-Dist: psycopg2<=2.9.6
Requires-Dist: django-postgres-extra<=2.0.8
Requires-Dist: django-dbbackup<=4.2.1
Requires-Dist: pymediainfo<=6.0.1
Requires-Dist: djangorangemiddleware<=1.0.1
Requires-Dist: django-typer[rich]<=2.4.0
Requires-Dist: dektools[dyna,encode,uid,yaml]<1.0.0
Requires-Dist: dynaconf[yaml]
